README.md
setup.cfg
setup.py
nuvo_simple/__init__.py
nuvo_simple.egg-info/PKG-INFO
nuvo_simple.egg-info/SOURCES.txt
nuvo_simple.egg-info/dependency_links.txt
nuvo_simple.egg-info/requires.txt
nuvo_simple.egg-info/top_level.txt