Metadata-Version: 2.4
Name: nuvo_simple
Version: 1.3.2
Summary: Python API for talking to "simple" Nuvo amplifiers
Home-page: https://github.com/brmcc/pynuvo-simple
Author: bmccrary
Author-email: bmccrary@shcircuit.com
Classifier: Programming Language :: Python :: 3
Classifier: License :: OSI Approved :: MIT License
Classifier: Operating System :: OS Independent
Requires-Dist: pyserial>=3.4
Dynamic: author
Dynamic: author-email
Dynamic: classifier
Dynamic: description
Dynamic: description-content-type
Dynamic: home-page
Dynamic: requires-dist
Dynamic: summary
